_streamvbyte.abi3.so
streamvbyte/__init__.py
streamvbyte/build.py
streamvbyte/lib.py
pystreamvbyte-0.4.1.dist-info/LICENSE
pystreamvbyte-0.4.1.dist-info/METADATA
pystreamvbyte-0.4.1.dist-info/WHEEL
pystreamvbyte-0.4.1.dist-info/top_level.txt
pystreamvbyte-0.4.1.dist-info/RECORD
